my_own_package/__init__.py
gsdolea_my_own_package-0.2.0.dist-info/METADATA
gsdolea_my_own_package-0.2.0.dist-info/WHEEL
gsdolea_my_own_package-0.2.0.dist-info/top_level.txt
gsdolea_my_own_package-0.2.0.dist-info/RECORD
