Metadata-Version: 2.1
Name: gsdolea-my-own-package
Version: 0.2.0
Summary: my_first_package
Author: geo dolea
Author-email: gsdolea@gmail.com
